<?xml version="1.0" encoding="utf-8"?>
<KinoveaToolbar>
  <FormatVersion>1.0</FormatVersion>
  <Name>Player</Name>
  <Id>93A56D9C-6B02-41AF-BF9B-33B1CAA1ADA3</Id>
  <entry name="Label">
    <subentry name="NumberSequence" />
  </entry>
  <entry name="Pencil" />
  <entry name="HumanModel">
    <subentry name="HumanModel2" />
    <subentry name="Bikefit" />
    <subentry name="Archery" />
    <subentry name="Profile" />
    <subentry name="Genu" />
    <subentry name="Posture" />
    <subentry name="CSVL" />
    <subentry name="Canis" />
    <subentry name="Equus" />
  </entry>
  <entry name="Line">
    <subentry name="Curve" />
    <subentry name="Polyline" />
    <subentry name="Rectangle" />
    <subentry name="Circle" />
    <subentry name="HorizontalDistance" />
  </entry>
  <entry name="Arrow">
    <subentry name="ArrowDash" />
    <subentry name="ArrowSquiggly" />
    <subentry name="ArrowCurve" />
    <subentry name="ArrowPolyline" />
    <subentry name="ArrowPolylineDash" />
    <subentry name="ArrowPolylineSquiggly" />
  </entry>
  <entry name="CrossMark" />
  <entry name="Angle">
    <subentry name="Goniometer" />
    <subentry name="AngleToHorizontal" />
    <subentry name="AngleToVertical" />
  </entry>
  <entry name="ChronoMulti">
    <subentry name="Clock" />
    <subentry name="TimeSegment" />
  </entry>
  <entry name="Plane">
    <subentry name="Grid" />
    <subentry name="DistanceGrid" />
    <subentry name="DistortionGrid" />
  </entry>
  <entry name="Spotlight" />
</KinoveaToolbar>